ise_openapi_endpoints/__init__.py
ise_openapi_endpoints/api_client.py
ise_openapi_endpoints/configuration.py
ise_openapi_endpoints/rest.py
ise_openapi_endpoints/api/__init__.py
ise_openapi_endpoints/api/endpoints_api.py
ise_openapi_endpoints/models/__init__.py
ise_openapi_endpoints/models/bulk_endpoints.py
ise_openapi_endpoints/models/device_type_entry.py
ise_openapi_endpoints/models/error.py
ise_openapi_endpoints/models/open_api_endpoint.py
ise_openapi_endpoints/models/task_response.py
ise_openapi_endpoints-0.1.2.dist-info/METADATA
ise_openapi_endpoints-0.1.2.dist-info/WHEEL
ise_openapi_endpoints-0.1.2.dist-info/RECORD
