Metadata-Version: 2.4
Name: ise-openapi-endpoints
Version: 0.1.2
Summary: Python Library for ISE Endpoints OpenApi API - Swagger Codegen Edition
Author-email: Thomas Christory <thomas@christory.net>
Requires-Python: >=3.10
Requires-Dist: certifi>=14.5.14
Requires-Dist: python-dateutil>=2.5.3
Requires-Dist: setuptools>=21.0.0
Requires-Dist: six>=1.10
Requires-Dist: urllib3>=1.15.1
